warpcompress/__init__.py
warpcompress/cli.py
warpcompress/core.py
warpcompress/pack.py
warpcompress-0.7.5.dist-info/licenses/LICENSE
warpcompress-0.7.5.dist-info/METADATA
warpcompress-0.7.5.dist-info/WHEEL
warpcompress-0.7.5.dist-info/entry_points.txt
warpcompress-0.7.5.dist-info/top_level.txt
warpcompress-0.7.5.dist-info/RECORD
