Metadata-Version: 2.4
Name: warpcompress
Version: 0.7.5
Summary: WarpCompress: adaptive, parallel (de)compression in pure Python with RAW/ZERO/LZ4/Snappy/Zstd per chunk, hybrid Zstd, and batched I/O.
Author-email: Shakeeb <you@example.com>
License: MIT
Requires-Python: >=3.8
License-File: LICENSE
Requires-Dist: python-snappy>=0.7.1
Requires-Dist: lz4>=4.3.2
Requires-Dist: zstandard>=0.22.0
Requires-Dist: brotli>=1.1.0
Provides-Extra: hashes
Requires-Dist: xxhash>=3.0.0; extra == "hashes"
Dynamic: license-file
